bvrLib/__init__.py
bvrLib/api.py
bvrLib/cronProfile.py
bvrLib/gpu-efficiency-profiler.py
bvrLib/minerProfile.py
bvrLib/powerProfile.py
bvrLib/set-power.py
bvrLib/start.mining.py
bvrLib/userProfile.py
bvrLib-2.0.dist-info/METADATA
bvrLib-2.0.dist-info/WHEEL
bvrLib-2.0.dist-info/top_level.txt
bvrLib-2.0.dist-info/RECORD
