Metadata-Version: 2.1
Name: bvrLib
Version: 2.0
Summary: bvr crypto mining API-s used by bvr mining code.
Home-page: https://bitbucket.org/guengn/bvrlib/src
Author: Guyen Gn
Author-email: guyen000@protonmail.com
License: MIT
Platform: UNKNOWN
